e_aws/__init__.py
e_aws/awsconnect.py
e_aws/awslambda.py
e_aws/awsresource.py
e_aws/awssession.py
e_aws/worker.py
e_aws/awsbucket/__init__.py
e_aws/awsbucket/awsbucket.py
e_aws/awsbucket/data_file.py
e_aws/awsbucket/data_list.py
e_aws/awsbucket/delete_object.py
e_aws/awsbucket/folder_upload.py
e_aws/awsbucket/metadata_type.py
e_aws/awsbucket/temp_file.py
e_aws-0.0.7.dist-info/METADATA
e_aws-0.0.7.dist-info/WHEEL
e_aws-0.0.7.dist-info/top_level.txt
e_aws-0.0.7.dist-info/RECORD
